
{
    "Ensembles" : {
        "nMembers" : 1},

    "Debug" : {
        "iVerbose" : 0,
        "iFunctionVerbose" : {
            "Grid::create_altitudes": 0},	
        "dt" : 10.0,
        "check_for_nans" : false
    },

    "EndTime" : [2011, 3, 20, 0, 10, 0],

    "GeoBlockSize" : {
        "nLons" : 18,
        "nLats" : 18,
        "nAlts" : 50},

    "neuGrid" : {
	"nLonsPerBlock" : 24,
	"nLatsPerBlock" : 22,
	"nAlts" : 40,
        "dAltScale" : 0.25,
        "IsUniformAlt" : false},
    
    "ionGrid": {
        "dAltScale": 0.2,
        "LatStretch": 6,
        "Shape": "dipole",
        "nLatsPerBlock" : 22,
        "nAlts":159,
        "LatMax":88,
        "MinAlt":100.0,
        "MinApex":150.0
        },

    "OmniwebFiles" : ["UA/inputs/omni_20110319.txt"],

    "Electrodynamics" : {
        "Potential" : "Weimer05",
        "DiffuseAurora" : "fta",
        "File": "UA/inputs/b20110320n_omni.bin"},
    
    "Outputs" : {
        "type" : ["states", "grid"],
        "dt" : [900, -1] },

    "DoCalcBulkIonTemp" : false,
    
    "PlanetFile" : "UA/inputs/earth.in"
    
}
